piccard/__init__.py
piccard/piccard.py
piccard/core/__init__.py
piccard/core/clustering.py
piccard/core/network.py
piccard/core/probabilistic_reasoning.py
piccard/linking/__init__.py
piccard/linking/multithreaded_mapping.py
piccard/linking/variable_linker.py
piccard/visualization/__init__.py
piccard/visualization/cluster_plots.py
piccard/visualization/network_visual.py
piccard-1.1.1.dist-info/METADATA
piccard-1.1.1.dist-info/WHEEL
piccard-1.1.1.dist-info/licenses/LICENSE
piccard-1.1.1.dist-info/RECORD
