Metadata-Version: 2.4
Name: piccard
Version: 1.1.1
Summary: Visualizing demographic evolution using geographically inconsistent census data
Project-URL: Homepage, https://github.com/ecorbin567/piccard2
Project-URL: Documentation, https://piccard.readthedocs.io/en/latest/
Project-URL: Research Paper, https://www.researchgate.net/publication/326137658_Visualizing_demographic_evolution_using_geographically_inconsistent_census_data
Author-email: Abdulmohseen AlAli <abdulmohseen.alali@gmail.com>, Elise Corbin <ecorbin567@gmail.com>, Maliha Lodi <maliha.f.lodi@gmail.com>
License-File: LICENSE
Classifier: License :: CC0 1.0 Universal (CC0 1.0) Public Domain Dedication
Classifier: Operating System :: OS Independent
Classifier: Programming Language :: Python :: 3
Requires-Python: >=3.7
Requires-Dist: geopandas
Requires-Dist: graphviz
Requires-Dist: hatchling
Requires-Dist: matplotlib
Requires-Dist: networkx
Requires-Dist: nltk
Requires-Dist: numpy
Requires-Dist: pandas
Requires-Dist: plotly
Requires-Dist: pyproj
Requires-Dist: scikit-learn
Requires-Dist: sentence-transformers
Requires-Dist: shapely
Requires-Dist: swifter
Requires-Dist: tscluster
Requires-Dist: typing-extensions
